gauss_bin_distrib/Binomialdistribution.py
gauss_bin_distrib/Gaussiandistribution.py
gauss_bin_distrib/Generaldistribution.py
gauss_bin_distrib/__init__.py
gauss_bin_distrib-0.2.dist-info/METADATA
gauss_bin_distrib-0.2.dist-info/WHEEL
gauss_bin_distrib-0.2.dist-info/top_level.txt
gauss_bin_distrib-0.2.dist-info/RECORD
